pspipe/__init__.py
pspipe/database.py
pspipe/obsdata.py
pspipe/settings.py
pspipe/tasks.py
pspipe/templates/config/eor_bins_a12.parset
pspipe/templates/config/eor_bins_alo.parset
pspipe/templates/config/eor_bins_hba.parset
pspipe/templates/config/eor_bins_nenufar.parset
pspipe/templates/config/flagger.parset
pspipe/templates/config/flagger_pre_combine.parset
pspipe/templates/config/gpr_config_a12.parset
pspipe/templates/config/gpr_config_hba.parset
pspipe/templates/config/gpr_config_nenufar.parset
pspipe/templates/config/gpr_config_v.parset
pspipe/templates/config/ps_config_a12.parset
pspipe/templates/config/ps_config_alo.parset
pspipe/templates/config/ps_config_hba.parset
pspipe/templates/config/ps_config_nenufar.parset
pspipe/templates/default_a12.toml
pspipe/templates/default_alo.toml
pspipe/templates/default_hba.toml
pspipe/templates/default_nenufar.toml
pspipe/templates/default_settings.toml
pspipe/tests/__init__.py
pspipe/tests/test_settings.py
pspipe/tests/test_utils.py
pspipe/tools/__init__.py
pspipe/tools/psdb.py
pspipe/tools/pspipe.py
pspipe/utils.py
pspipe-0.5.1.dist-info/LICENSE
pspipe-0.5.1.dist-info/METADATA
pspipe-0.5.1.dist-info/WHEEL
pspipe-0.5.1.dist-info/entry_points.txt
pspipe-0.5.1.dist-info/RECORD
