Metadata-Version: 2.1
Name: pspipe
Version: 0.5.1
Summary: Power spectra pipeline for Cosmic Dawn, Epoch of Reionization radio interferometric experiments
Home-page: https://gitlab.com/flomertens/pspipe/
Author: "Florent Mertens"
Author-email: "florent.mertens@gmail.com"
Requires-Python: >=3.8,<4.0
Classifier: Programming Language :: Python :: 3
Classifier: Programming Language :: Python :: 3.8
Classifier: Programming Language :: Python :: 3.9
Classifier: Programming Language :: Python :: 3.10
Classifier: Programming Language :: Python :: 3.11
Classifier: Programming Language :: Python :: 3.12
Requires-Dist: GPy (>=1.10,<2.0,!=1.12.0)
Requires-Dist: astropy (>=5.0,<7.0)
Requires-Dist: matplotlib (>=3.0,<4.0)
Requires-Dist: nenucal (>=0.1.11)
Requires-Dist: ps-eor (>=0.8)
Requires-Dist: python-casacore (>=3.0,<4.0)
Requires-Dist: scipy (>=1.8,<2.0)
Requires-Dist: tables (>=3.2,<4.0)
Requires-Dist: tabulate (>=0.8)
Requires-Dist: toml (>=0.10)
Project-URL: Repository, https://gitlab.com/flomertens/pspipe/
